myVOCRec/__init__.py
myVOCRec-1.dist-info/METADATA
myVOCRec-1.dist-info/WHEEL
myVOCRec-1.dist-info/top_level.txt
myVOCRec-1.dist-info/RECORD
