Metadata-Version: 2.1
Name: myVOCRec
Version: 1
Summary: Capturing Microphone Data into an Audio File
Home-page: https://github.com/Shahabks/myspokenlanguageid
Author: Shahab Sabahi
Author-email: sabahi.s@mysol-gc.jp
License: MIT
Keywords: speech signal processing,Natural Language Processing and Understanding,Voice-Recorder
Platform: UNKNOWN
Classifier: Intended Audience :: Developers
Classifier: Intended Audience :: Science/Research
Classifier: Programming Language :: Python
Classifier: Programming Language :: Python :: 3.7
Requires-Dist: sounddevice (>=0.3.12)
Requires-Dist: SoundFile (>=0.10.2)
